Number_Square/square.py
Number_Square-1.0.2.dist-info/LICENSE
Number_Square-1.0.2.dist-info/METADATA
Number_Square-1.0.2.dist-info/WHEEL
Number_Square-1.0.2.dist-info/top_level.txt
Number_Square-1.0.2.dist-info/RECORD
